{
  "initial_prompt": "Create the game 'pong' using the programming language: Python.",
  "tasks": [
    {
      "task_number": 1,
      "main_task": "1. **Create a game window.** This can be done using the `pygame` library.",
      "completed": true
    },
    {
      "task_number": 2,
      "main_task": "2. **Draw the paddles and the ball.** The paddles can be represented by rectangles, and the ball can be represented by a circle.",
      "completed": true
    },
    {
      "task_number": 3,
      "main_task": "3. **Handle user input.** This includes moving the paddles and starting and stopping the game.",
      "completed": true
    },
    {
      "task_number": 4,
      "main_task": "4. **Update the game state.** This includes moving the ball and checking for collisions.",
      "completed": true
    },
    {
      "task_number": 5,
      "main_task": "5. **Draw the game to the screen.** This is done by calling the `pygame.display.update()` function.",
      "completed": true
    },
    {
      "task_number": 6,
      "main_task": "6. **Run the game loop.** This is the main loop of the game, and it repeats until the user quits the game.",
      "completed": false
    }
  ],
  "subtasks": [
    {
      "task_number": 1,
      "subtask_number": 1,
      "main_task": "1. Import the pygame library.",
      "completed": false
    },
    {
      "task_number": 1,
      "subtask_number": 2,
      "main_task": "2. Create a display surface.",
      "completed": false
    },
    {
      "task_number": 1,
      "subtask_number": 3,
      "main_task": "3. Set the display mode.",
      "completed": false
    },
    {
      "task_number": 1,
      "subtask_number": 4,
      "main_task": "4. Initialize the pygame library.",
      "completed": false
    },
    {
      "task_number": 1,
      "subtask_number": 5,
      "main_task": "5. Create a clock object.",
      "completed": false
    },
    {
      "task_number": 1,
      "subtask_number": 6,
      "main_task": "6. Start the main loop.",
      "completed": false
    },
    {
      "task_number": 2,
      "subtask_number": 1,
      "main_task": "1. **Create a new document.**",
      "completed": false
    },
    {
      "task_number": 2,
      "subtask_number": 2,
      "main_task": "2. **Select the **Rectangle** tool.**",
      "completed": false
    },
    {
      "task_number": 2,
      "subtask_number": 3,
      "main_task": "3. **Draw a rectangle in the center of the document.**",
      "completed": false
    },
    {
      "task_number": 2,
      "subtask_number": 4,
      "main_task": "4. **Select the **Ellipse** tool.**",
      "completed": false
    },
    {
      "task_number": 2,
      "subtask_number": 5,
      "main_task": "5. **Draw a circle in the center of the rectangle.**",
      "completed": false
    },
    {
      "task_number": 3,
      "subtask_number": 1,
      "main_task": "1. **Get the current state of the keyboard and mouse.**",
      "completed": false
    },
    {
      "task_number": 3,
      "subtask_number": 2,
      "main_task": "2. **Check if any keys are pressed.**",
      "completed": false
    },
    {
      "task_number": 3,
      "subtask_number": 3,
      "main_task": "3. **If a key is pressed, move the corresponding paddle accordingly.**",
      "completed": false
    },
    {
      "task_number": 3,
      "subtask_number": 4,
      "main_task": "4. **Check if the \"start\" or \"stop\" button is pressed.**",
      "completed": false
    },
    {
      "task_number": 3,
      "subtask_number": 5,
      "main_task": "5. **If the \"start\" button is pressed, start the game.**",
      "completed": false
    },
    {
      "task_number": 3,
      "subtask_number": 6,
      "main_task": "6. **If the \"stop\" button is pressed, stop the game.**",
      "completed": false
    },
    {
      "task_number": 4,
      "subtask_number": 1,
      "main_task": "1. **Get the current position of the ball.**",
      "completed": false
    },
    {
      "task_number": 4,
      "subtask_number": 2,
      "main_task": "2. **Calculate the new position of the ball based on its velocity.**",
      "completed": false
    },
    {
      "task_number": 4,
      "subtask_number": 3,
      "main_task": "3. **Check if the ball has collided with any of the game objects.**",
      "completed": false
    },
    {
      "task_number": 4,
      "subtask_number": 4,
      "main_task": "4. **If the ball has collided with an object, apply the appropriate collision response.**",
      "completed": false
    },
    {
      "task_number": 4,
      "subtask_number": 5,
      "main_task": "5. **Update the game state.**",
      "completed": false
    },
    {
      "task_number": 5,
      "subtask_number": 1,
      "main_task": "1. Create a pygame window.",
      "completed": false
    },
    {
      "task_number": 5,
      "subtask_number": 2,
      "main_task": "2. Create a pygame surface.",
      "completed": false
    },
    {
      "task_number": 5,
      "subtask_number": 3,
      "main_task": "3. Draw the game objects to the surface.",
      "completed": false
    },
    {
      "task_number": 5,
      "subtask_number": 4,
      "main_task": "4. Update the display.",
      "completed": false
    },
    {
      "task_number": 6,
      "subtask_number": 1,
      "main_task": "1. **Initialize the game.** This includes creating the game window, loading the game assets, and initializing the game state.",
      "completed": false
    },
    {
      "task_number": 6,
      "subtask_number": 2,
      "main_task": "2. **Handle user input.** This includes checking for keyboard and mouse input, and responding to it appropriately.",
      "completed": false
    },
    {
      "task_number": 6,
      "subtask_number": 3,
      "main_task": "3. **Update the game state.** This includes updating the position of the game objects, checking for collisions, and resolving any conflicts.",
      "completed": false
    },
    {
      "task_number": 6,
      "subtask_number": 4,
      "main_task": "4. **Render the game state.** This includes drawing the game objects to the screen, and updating the game HUD.",
      "completed": false
    },
    {
      "task_number": 6,
      "subtask_number": 5,
      "main_task": "5. **Check for game over.** If the player has lost the game, this step will exit the game loop.",
      "completed": false
    },
    {
      "task_number": 6,
      "subtask_number": 6,
      "main_task": "6. **Repeat steps 2-5 until the game is over.**",
      "completed": false
    }
  ],
  "code_snippets": [],
  "summary": "User prompt: Create the game 'pong' using the programming language: Python.\nConversation summary:\nTask 1: 1. **Create a game window.** This can be done using the `pygame` library. (completed)\n- Subtask 1: 1. Import the pygame library.\n- Subtask 2: 2. Create a display surface.\n- Subtask 3: 3. Set the display mode.\n- Subtask 4: 4. Initialize the pygame library.\n- Subtask 5: 5. Create a clock object.\n- Subtask 6: 6. Start the main loop.\n\nTask 2: 2. **Draw the paddles and the ball.** The paddles can be represented by rectangles, and the ball can be represented by a circle. (completed)\n- Subtask 1: 1. **Create a new document.**\n- Subtask 2: 2. **Select the **Rectangle** tool.**\n- Subtask 3: 3. **Draw a rectangle in the center of the document.**\n- Subtask 4: 4. **Select the **Ellipse** tool.**\n- Subtask 5: 5. **Draw a circle in the center of the rectangle.**\n\nTask 3: 3. **Handle user input.** This includes moving the paddles and starting and stopping the game. (completed)\n- Subtask 1: 1. **Get the current state of the keyboard and mouse.**\n- Subtask 2: 2. **Check if any keys are pressed.**\n- Subtask 3: 3. **If a key is pressed, move the corresponding paddle accordingly.**\n- Subtask 4: 4. **Check if the \"start\" or \"stop\" button is pressed.**\n- Subtask 5: 5. **If the \"start\" button is pressed, start the game.**\n- Subtask 6: 6. **If the \"stop\" button is pressed, stop the game.**\n\nTask 4: 4. **Update the game state.** This includes moving the ball and checking for collisions. (completed)\n- Subtask 1: 1. **Get the current position of the ball.**\n- Subtask 2: 2. **Calculate the new position of the ball based on its velocity.**\n- Subtask 3: 3. **Check if the ball has collided with any of the game objects.**\n- Subtask 4: 4. **If the ball has collided with an object, apply the appropriate collision response.**\n- Subtask 5: 5. **Update the game state.**\n\nTask 5: 5. **Draw the game to the screen.** This is done by calling the `pygame.display.update()` function. (completed)\n- Subtask 1: 1. Create a pygame window.\n- Subtask 2: 2. Create a pygame surface.\n- Subtask 3: 3. Draw the game objects to the surface.\n- Subtask 4: 4. Update the display.\n\nTask 6: 6. **Run the game loop.** This is the main loop of the game, and it repeats until the user quits the game.\n- Subtask 1: 1. **Initialize the game.** This includes creating the game window, loading the game assets, and initializing the game state.\n- Subtask 2: 2. **Handle user input.** This includes checking for keyboard and mouse input, and responding to it appropriately.\n- Subtask 3: 3. **Update the game state.** This includes updating the position of the game objects, checking for collisions, and resolving any conflicts.\n- Subtask 4: 4. **Render the game state.** This includes drawing the game objects to the screen, and updating the game HUD.\n- Subtask 5: 5. **Check for game over.** If the player has lost the game, this step will exit the game loop.\n- Subtask 6: 6. **Repeat steps 2-5 until the game is over.**\n\n",
  "subtasks_1": [],
  "subtasks_2": [],
  "subtasks_3": [],
  "subtasks_4": [],
  "subtasks_5": [],
  "subtasks_6": [],
  "task_summary": "Task 1 '2. **Draw the paddles and the ball.** The paddles can be represented by rectangles, and the ball can be represented by a circle.' was completed.\nTask 2 '3. **Handle user input.** This includes moving the paddles and starting and stopping the game.' was completed.\nTask 3 '4. **Update the game state.** This includes moving the ball and checking for collisions.' was completed.\nTask 4 '5. **Draw the game to the screen.** This is done by calling the `pygame.display.update()` function.' was completed.\nTask 5 '6. **Run the game loop.** This is the main loop of the game, and it repeats until the user quits the game.' was completed.\n"
}